setup.py
general_distribution_functions/Bionomial_Distribution.py
general_distribution_functions/Distribution.py
general_distribution_functions/Gaussian_Distribution.py
general_distribution_functions/__init__.py
general_distribution_functions.egg-info/PKG-INFO
general_distribution_functions.egg-info/SOURCES.txt
general_distribution_functions.egg-info/dependency_links.txt
general_distribution_functions.egg-info/not-zip-safe
general_distribution_functions.egg-info/top_level.txt