Metadata-Version: 1.0
Name: general-distribution-functions
Version: 0.1
Summary: Gaussian_binomial_ distributions
Home-page: UNKNOWN
Author: Ahmed Safwat
Author-email: UNKNOWN
License: UNKNOWN
Platform: UNKNOWN
